{
    "done": "Готово",
    "ok": "Ок",
    "cancel": "Отмена",
    "close": "Закрыть",
    "copy": "Скопировать",
    "no_internet_connection": "Нет интернета",
    "main_menu_wallet": "Кошелек",
    "main_menu_exchange": "Биржа",
    "main_menu_learn": "Learn",
    "main_wallet_my_wallet": "Кошелек",
    "main_wallet_total_title": "Стоимость всех активов",
    "main_wallet_manage_accounts": "Управление счетами",
    "main_wallet_restore": "Востановить",
    "main_wallet_have_wallet_already": "Уже есть кошелек?",
    "main_wallet_recent_transactions": "Последние транзакции",
    "main_wallet_wallet_wallet_view_all": "Все",
    "main_wallet_safety_tips": "Полезные советы",
    "main_wallet_more_things": "И еще",
    "main_wallet_feedback": "Написать отзыв",
    "main_wallet_advanced_features": "Расширенные функции",
    "main_wallet_settings_and_support": "Настройки и техподдержка",
    "main_wallet_my_ether_wallet_inc": "MyEtherWallet Inc. это независимая компания которая ни кем кроме нас самих не финансируется. Mew wallet это бесплатный инструмент для взаимодействия с блокчейном.\\n Все наши продукты — с открытым кодом. Мы не собираем и не храним у себя никакой личной информации, ключей или паролей. Мы никак ваши данные не монетизируем (потому что у нас их попросту нет), и не используем их для маркетинга или рекламы.",
    "main_wallet_wallets_tokens_zero": "Токенов",
    "main_wallet_wallets_tokens_one": "Токен",
    "main_wallet_wallets_tokens_two": "Токена",
    "main_wallet_wallets_tokens_few": "Токена",
    "main_wallet_wallets_tokens_many": "Токенов",
    "main_wallet_wallets_tokens_other": "Токена",
    "main_wallet_coming_soon": "В разработке…",
    "main_wallet_guide_title": "Эфириум, что\\u00A0это вообще такое? Максимально понятно для новичков",
    "main_wallet_feedback_subject": "MEW Wallet v.%s (%d) Android feedback",
    "main_wallet_feedback_text": "\\n***\\nПожалуйста, как можно больше подробностей, желательно со скриншотами или видео.\\n***\\n\\nТо, что ниже не стирайте, мы так сможем быстрее разобраться:\\n%1$s, Android %2$s, Размер экрана: %3$dx%4$d, Страна %5$s%6$s, v.%7$s (%8$d)\\n\\nСпасибо за терпение!\\n~Мобильная команда MEW.",
    "main_wallet_info_text": "Этот материал и многое другое останется доступным в\\nЦентре обучения",
    "main_wallet_samsung_error_text": "Ошибка %d, обратитесь в техподдержку",
    "main_wallet_samsung_error_button": "Обратиться",
    "main_wallet_receive_tab_title": "Получить",
    "main_wallet_receive_tab_desc": "Из другого кошелька",
    "main_wallet_buy_tab_title": "Купить Эфир",
    "main_wallet_buy_tab_desc": "по банковской карте",
    "main_wallet_astronaut_chat": "Для начала\\nдобавьте в кошелек\\nнемного Эфира",
    "main_wallet_samsung_blockchain": "Пожалуйста, обновите Samsung Blockchain",
    "main_wallet_keystore_updated": "Требуется обновить Keystore перед использованием",
    "samsung_link_dialog_title": "Подсоединить к Samsung\\nBlockchain Keystore",
    "samsung_link_dialog_text": "На этом устройстве есть Samsung Blockchain Keystore — самый безопасный способ хранения всех ваших крипто-ключей. Вы можете подсоединить приложение к Keystore, или создать свежий кошелек и хранить ключи локально на\\u00A0устройстве.",
    "samsung_link_dialog_ok": "Подсоединить",
    "samsung_link_dialog_cancel": "Создать свежий кошелек",
    "samsung_link_dialog_mewconnect": "Импортировать из MEWconnect",
    "crypto_safety_101": "Курс молодого крипто-бойца",
    "crypto_safety_item_number1": "1",
    "crypto_responsibility": "В крипто-мире каждый сам себе хозяин, банкир и брокер. Полная свобода это здорово, но отвечать тоже за все придется самому.",
    "crypto_back_it_up": "Сделайте резервную копию кошелька и храните ее как зеницу\\u00A0ока",
    "crypto_warning": "Если вы потеряли телефон, и у вас нет резервной копии, никто (!) не сможет восстановить ваш кошелек и вы потеряете все свои сбережения. Наша техподдержка в таких случаях бессильна.",
    "crypto_safety_item_number2": "2",
    "crypto_safety_item_title2": "Всегда все перепроверяйте по нескольку раз",
    "crypto_safety_item_text2": "Если вы случайно отправите средства на неправильный адрес, никто уже не поможет и отменить эту транзакцию, к сожалению, не удастся.",
    "crypto_safety_item_number3": "3",
    "crypto_phishing_and_scams": "Берегитесь мошенников и аферистов",
    "crypto_something_good": "На всякий случай никому не верьте, особенно если вам предлагают что-то что звучит слишком хорошо чтобы быть правдой.",
    "crypto_safe_out": "Берегите себя!\\n~Команда MEW",
    "crypto_create_a_wallet": "создать кошелек",
    "create_pin_toolbar": "Создать кошелек",
    "create_pin_title": "Придумайте ПИН-код",
    "recovery_phrase_pin_title": "Придумайте ПИН-код",
    "create_pin1_header": "Чтобы никто кроме вас не мог зайти к\\u00A0вам в\\u00A0кошелек.",
    "create_pin1_footer_not_learn_more": "ПИН-коды дают защиту не хуже длинных паролей, а запоминать их гораздо проще.",
    "type_your_pin_title": "Введите ПИН еще разок",
    "create_pin2_header": "В приложении <u>НЕТ кнопки «Я забыл ПИН-код»<\/u><br\/>Убедитесь, что вы хорошенько его запомнили.",
    "create_pin2_footer": "Поскольку в крипто вы сами себе хозяин и банкир, мы не сможем вам помочь если вы забудете свой ПИН-код.",
    "enable_fingerprint_title": "Включить биометрическую разблокировку",
    "enable_fingerprint_access": "Входите в свой кошелек по биометрическим данным.\\nБыстро, просто и безопасно.",
    "enable_fingerprint_button": "включить биометрию",
    "enable_fingerprint_how_secure": "<u>А это точно безопасно?<\/u>",
    "enable_fingerprint_skip": "пропустить",
    "secure_pin_title": "Что безопаснее, ПИН или пароль?",
    "secure_pin_text1": "ПИН-код (или Персональный Идентификационный Номер) хорошая замена паролю. Он состоит только из цифр, его просто запомнить и проще ввести с клавиатуры.",
    "secure_pin_text2": "Несмотря на то что возможных комбинаций в ПИН-кодах гораздо меньше чем в паролях, важно помнить что количество попыток ввода ограничено, а сам ПИН-код хранится в зашифрованном виде в глубинах телефона, откуда его практически невозможно достать. Поэтому стандартный метод быстрого перебора паролей невозможно запустить на телефоне (если конечно у вас не включен рут-доступ. Вы не хакер? Специально ничего со своим телефоном не делали? Тогда все в порядке, во всех телефонах рут-доступ по-умолчанию отключен и включить его не так просто). \nЕще есть защита самого телефона, на нем ведь тоже установлен ПИН (горячо рекомендуем не ставить на сам телефон и на приложение одинаковые ПИН-коды), который тоже можно ввести только ограниченное количество раз.",
    "secure_pin_text3": "Несмотря на то, что на первый взгляд пароли кажутся более надежными, благодаря ограничению на количество попыток ввода, ПИН-коды могут неплохо с ними посоревноваться.",
    "secure_pin_text4": "Запоминать ПИН-коды проще, вводить тоже, поэтому мы их и выбрали для нашего приложения. \nЕдинственный момент: придумайте себе пин посложнее, чтобы его нельзя было угадать. «123456», «111111», «147258» — не самые лучшие варианты.",
    "generating_start_using": "Начать пользоваться",
    "generating_start_animation_text1_generating": "Генерируем ваш<br\/><font color=\"#08c3a5\">Эфириум-адрес<\/font>",
    "generating_start_animation_text1_restoring": "Восстанавливаем ваш<br\/><font color=\"#08c3a5\">кошелек<\/font>",
    "generating_start_animation_text1_importing": "Импортируем ваш<br\/><font color=\"#08c3a5\">кошелек<\/font>",
    "generating_start_animation_text2": "Зашифровываем ваш<br\/><font color=\"#08c3a5\">закрытый ключ<\/font><br\/>вашим ПИН-кодом",
    "generating_start_animation_text3": "Сохраняем ваши<br\/>зашифрованные ключи в<br\/><font color=\"#08c3a5\">защищенное хранилище<\/font><br\/>локально на этом устройстве",
    "generating_start_animation_text4": "Кошелек готов!<br\/><font color=\"#08c3a5\">Можно начинать пользоваться.<\/font>",
    "lets_double_check_item_title": "Отметьте слово №%d",
    "dialog_pin_unlocked_title": "Введите ПИН-код",
    "dialog_pin_locked_title": "Многовато неверных попыток",
    "dialog_pin_locked_message": "Подождите:",
    "back_up_button_now": "Сделать резервную копию",
    "back_up_your_wallet_title": "Резервная копия кошелька",
    "back_up_your_wallet_text1": "С кошельком MEW вы сами себе хозяин и банкир. Ни у кого кроме вас нет доступа к вашему закрытому ключу и вашим сбережениям. Даже у нашей техподдержки.",
    "back_up_your_wallet_text2": "Если у вас нет резервной копии и вы потеряли телефон, или, даже, просто удалили наше приложение, вы навсегда потеряете свои сбережения.",
    "backed_up_your_wallet_title": "Резервная копия создана!",
    "backed_up_your_wallet_text": "Храните свою кодовую фразу как зеницу ока. В этой фразе – ключи от всех ваших аккаунтов. Никому ее не давайте, ни на каких сайтах не вводите. Даже нашей техподдержке. Вообще никому.",
    "backed_up_your_wallet_button": "Готово",
    "double_check_text": "Кодовую фразу можно будет посмотреть снова в Настройках.",
    "double_check_title": "Давайте проверим",
    "double_check_finish": "Готово",
    "recovery_phrase_title": "Это ваша\\n кодовая фраза",
    "recovery_phrase_subtitle": "Запишите эти слова на листке бумаги, и храните где-нибудь в безопасном месте.",
    "recovery_phrase_next": "Далее",
    "prepare_to_write_title": "Приготовьтесь записать свою кодовую фразу",
    "prepare_to_write_text1": "Если вы потеряете телефон или случайно удалите приложение, все аккаунты в вашем кошельке можно будет восстановить с помощью кодовой фразы.",
    "prepare_to_write_text2": "Приготовьте ручку и листок бумаги.",
    "prepare_to_write_button_start": "начать",
    "prepare_to_write_pin_title": "Введите ПИН-код",
    "prepare_to_write_biometry_title": "Нужно ваше подтверждение",
    "main_wallet_backup_now": "сделать резервную копию",
    "main_wallet_backup_title": "Важно: сделайте резервную копию",
    "main_wallet_backup_text": "Если вы потеряете телефон, или случайно удалите приложение все ваши сбережения безвозвратно пропадут.",
    "scan_toolbar_title": "Сканер QR-кодов",
    "scan_camera_permission_rationale_settings1": "Пожалуйста, дайте MEW wallet-у доступ к камере в\\u00A0",
    "scan_camera_permission_rationale_settings2": "Настройках",
    "scan_camera_permission_rationale_settings3": "\" \"",
    "scan_camera_permission_rationale_dialog1": "Пожалуйста\\u00A0",
    "scan_camera_permission_rationale_dialog2": "разрешите доступ к камере",
    "scan_camera_permission_rationale_dialog3": "\\u00A0для\\nMEW wallet-а",
    "scan_error_try_again": "Попробуйте снова",
    "scan_offline": "Нет интернета",
    "scan_error_contact": "Обратиться в техподдержку",
    "create_wallet_title": "Создать кошелек",
    "create_wallet_description": "Кошелек нужен чтобы хранить и\\u00A0покупать Эфир, обменивать токены на\\u00A0бирже\\u00A0и\\u00A0др.",
    "create_wallet_default_name": "Основной аккаунт",
    "create_biometry_title": "Включить биометрическую разблокировку",
    "biometric_prompt_cancel": "Отмена",
    "biometric_data_was_changed": "Биометрическая информация поменялась",
    "address_format": "%1$s···%2$s",
    "available_assets_toolbar": "Мои токены",
    "available_asset_network": "Эфириум",
    "send_progress_to": "Кому:",
    "too_low_title": "На этом аккаунте недостаточно Эфира",
    "too_low_text": "Чтобы отправить транзакцию вам понадобится немного Эфира, даже если вы отправляете не сам Эфир а токены. Поэтому нужно всегда иметь немного Эфира на счету.",
    "too_low_button": "Пополнить счет",
    "transaction_fee_title": "Выбор комиссии",
    "verify_transaction_check_address_button": "Все верно, отправляем",
    "verify_transaction_fee_total": "Итого:",
    "verify_transaction_fee": "Комиссия:",
    "verify_swap_fee_description": "Показана максимально возможная комиссия. Скорее всего всего реальная комиссия будет на 20-70% ниже.",
    "verify_transaction_check_amount": "Проверьте сумму",
    "verify_transaction_check_the_address": "Проверьте адрес",
    "verify_transaction_from": "от",
    "verify_transaction_text": "После отправки отменить транзакцию будет уже нельзя",
    "verify_transaction_title": "Проверьте, все\\u00A0ли\\u00A0правильно",
    "verify_transaction_pin_title": "Введите ПИН-код",
    "verify_transaction_biometry_title": "Подтвердите отправку",
    "verify_transaction_check_address_and_amount": "Подтвердите сумму и адрес",
    "choose_recepient_toolbar": "Отправить",
    "choose_recepient_cards": "Мои счета",
    "choose_recepient_recent": "Недавние",
    "choose_recepient_scan": "Сканировать",
    "choose_recepient_paste": "Вставить",
    "choose_recepient_text": "Эфириум-адрес",
    "choose_recepient_error": "Непохоже, что это правильный адрес",
    "send_bottom_sheet_title": "Мои счета",
    "send_input_amount_keyboard_symbol_1": "1",
    "send_input_amount_keyboard_symbol_2": "2",
    "send_input_amount_keyboard_symbol_3": "3",
    "send_input_amount_keyboard_symbol_4": "4",
    "send_input_amount_keyboard_symbol_5": "5",
    "send_input_amount_keyboard_symbol_6": "6",
    "send_input_amount_keyboard_symbol_7": "7",
    "send_input_amount_keyboard_symbol_8": "8",
    "send_input_amount_keyboard_symbol_9": "9",
    "send_input_amount_keyboard_symbol_0": "0",
    "send_input_amount_keyboard_symbol_point": ".",
    "send_input_amount_enter_amount_button_sum": "Send %1$s %2$s",
    "send_input_amount_enter_amount_button_default": "Enter amount",
    "send_input_amount_total": "Total:",
    "send_input_amount_max_button": "Max",
    "send_input_amount_amount_main_zero": "0",
    "send_input_amount_not_enough_to_pay": "Not enough ETH to pay the fee",
    "send_input_amount_buy_ether": "Buy Ether",
    "send_input_less_than": "less than %s",
    "transition_fee_less_than": "<%s",
    "transition_fee_not_enough_funds": "Not enough funds",
    "transition_fee_mode_economy": "Economy",
    "transition_fee_mode_regular": "Regular",
    "transition_fee_mode_fast": "Fast",
    "transition_fee_minutes": "%d min",
    "scan_address_title": "Scan QR code",
    "scan_address_pick_image": "Select Picture",
    "scan_address_search_title": "Search",
    "scan_address_recognize": "Can\\'t recognize QR",
    "scan_address_unknown_qr": "Unknown QR",
    "exchange_title": "Биржа",
    "exchange_tab_market": "Market",
    "exchange_tab_swap_history": "History",
    "exchange_search_hint": "Search tokens",
    "exchange_swap_tokens": "Swap tokens",
    "exchange_swap_tokens_new": "New",
    "exchange_buy_ether": "Buy Ether",
    "exchange_visa_mastercard": "Visa or Mastercard",
    "exchange_market_search_at_least_characters": "Type at least 2 characters",
    "exchange_market_search_no_results": "No results",
    "swap_history_status_exchanging": "Exchanging",
    "swap_history_status_swapped": "Swapped",
    "swap_history_status_failed": "Failed",
    "swap_unavailable": "Swap unavailable",
    "swap_select_token": "Select token",
    "swap_tokens_rate": "%1$s ≈ %2$s ≈ \\$%3$s",
    "swap_tokens_button_enter_amount": "Enter amount and select token",
    "swap_tokens_button_unavailable": "swap unavailable for this pair",
    "swap_tokens_button_checking": "Checking rates…",
    "swap_tokens_button_find_best": "Find best rate",
    "swap_tokens_rate_unavailable": "Swap temporarily unavailable due to low liquidity.",
    "swap_verify_fee_error": "Swap temporarily unavailable. Please try again later",
    "view_token_input_max": "Max",
    "desired_token_title": "Token you want to get",
    "available_assets_title": "Available assets",
    "available_assets_no_results": "No results",
    "select_rate_title": "Select rate and provider",
    "select_rate_fee": "Quotes are approximate, and include 2.5% fee",
    "select_rate_for": "for",
    "select_rate_you_will_get": "you will get:",
    "select_rate_best": "Best rate",
    "select_rate_unavailable": "Temporarily unavailable",
    "select_rate_multiple_dex": "Splits your order across multiple DEXes",
    "verify_swap_title": "Verify swap",
    "verify_swap_deposit_to": "Deposit %s to",
    "verify_swap_provider": "Provider: %s",
    "verify_swap_exchange_rate": "Exchange rate:",
    "verify_swap_wait_time": "Provider wait time:",
    "verify_swap_button": "Proceed with swap",
    "verify_swap_show_more": "Show more",
    "verify_swap_show_less": "Show less",
    "verify_swap_get_text": "You will get",
    "verify_swap_you_swap_text": "You swap",
    "verify_swap_provider_description": "You receive at least %s or swap will fail.",
    "verify_swap_pin_title": "Enter PIN to swap",
    "verify_swap_biometry_title": "Confirm to swap",
    "choose_deposit_title": "Choose deposit address",
    "choose_address_external_account": "Внешний адрес",
    "choose_address_external_description": "Please make sure its ERC-20 compatible\\naccount",
    "choose_address_personal_account": "Мой личный счет",
    "swap_initiated": "Swap initiated",
    "swap_initiated_description": "Once its completed, %s will be deposited \\nto the address you specified",
    "swap_initiated_view_progress": "View progress",
    "swap_details_title": "Swap details",
    "swap_details_provider": "Provider details",
    "swap_details_etherscan": "View on Etherscan",
    "swap_details_header_from": "FROM",
    "swap_details_header_to": "TO",
    "swap_details_status_swapped": "Tokens successfully swapped",
    "swap_details_status_exchanging": "Exchanging…",
    "swap_details_status_failed": "Failed",
    "view_swap_status_contact_support": "Contact support",
    "view_swap_feedback_subject": "MEW Wallet v.%1$s (%2$d) Android Swap Fail Transaction hash: %3$s",
    "account_details_status_tab_assets": "Assets",
    "account_details_status_tab_transaction": "Transactions",
    "account_details_at": "\\@",
    "account_details_buy_ether": "Buy Ether",
    "account_details_send": "Send",
    "account_details_receive": "Receive",
    "account_details_time": "%d:%02d",
    "account_details_astronaut_chat": "Zero ETH means zero fun. Add some Ether to your wallet to get started",
    "account_assets_total_tokens_title": "Total tokens",
    "account_assets_empty": "No assets",
    "account_summary_total_value": "Total value",
    "account_summary_ether": "Ether",
    "account_summary_tokens": "Tokens",
    "account_summary_1_hour": "1h",
    "account_summary_24_hours": "24h",
    "account_summary_1_week": "1w",
    "account_summary_1_month": "1m",
    "account_summary_1_year": "1y",
    "account_summary_all": "All",
    "account_summary_changes_this_week": "Changes this week",
    "account_transaction_received": "Received",
    "account_transaction_sent_to": "Sent",
    "account_transaction_failed": "Failed",
    "account_transaction_self": "Self",
    "account_transaction_dy_ago": " %dy ago",
    "account_transaction_dw_ago": " %dw ago",
    "account_transaction_dd_ago": " %dd ago",
    "account_transaction_dh_ago": " %dh ago",
    "account_transaction_dm_ago": " %dm ago",
    "account_transaction_less_minute_ago": "less than a minute ago",
    "account_transaction_sending": "Sending %d:%02d",
    "account_transaction_empty": "Здесь будут показаны\\nтранзакции по\\u00A0вашему\\u00A0счету",
    "add_account_description": "Например: Личные сбережения, Работа, Инвестиции, Секретный счет,\\u00A0и\\u00A0т.\\u00A0п.",
    "add_account_card_title": "Добавить счет",
    "add_account_card_description_text_1": "To manage your stacks separately",
    "add_account_card_description_text_2": "For example",
    "add_account_card_description_text_3": "Day-to-day payments, Long-term savings, dApp\\nplay funds",
    "add_account_edit_hint": "Название счета",
    "add_account_button": "Add",
    "add_account_pin_title": "Enter PIN to add",
    "add_account_biometry_title": "Confirm to add",
    "confirm_transaction_network_title": "Check network",
    "confirm_transaction_text": "If your computer is compromised, attackers might replace ‘Send to’ address with their own, before sending your transaction. That’s why it’s important to check it in MEWconnect.",
    "confirm_transaction_decline": "Decline",
    "confirm_transaction_ok": "Confirm",
    "confirm_transaction_network_unknown": "Unknown network",
    "confirm_transaction_pin_title": "Enter PIN to confirm",
    "confirm_transaction_biometry_title": "Please confirm",
    "confirm_transaction_unknown": "UNKNOWN",
    "accounts_title": "Select funds from",
    "connect_to_desktop_text_1": "Go to <b>MyEtherWallet.com<\/b> on your computer",
    "connect_to_desktop_text_2": "Choose Access <b>My Wallet<\/b><br\/>option",
    "connect_to_desktop_text_3": "Select <b>MEW Connect<\/b> option on the screen that follows",
    "connect_to_desktop_text_4": "Scan the QR code with your<br\/>mobile device",
    "connect_to_desktop_title": "How to connect to\\nMEW web",
    "connect_to_desktop_text": "MEW wallet app can seamlessly connect to MEW web, so you can access all advanced features, while keeping your keys safely on your mobile device.",
    "connect_to_desktop_position_1": "1",
    "connect_to_desktop_position_2": "2",
    "connect_to_desktop_position_3": "3",
    "connect_to_desktop_position_4": "4",
    "continue_title": "Continue in your browser",
    "continue_text": "The message is signed. Please continue in MyEtherWallet in your browser.",
    "sign_message_title": "Sign message",
    "sign_message_description": "Please remember to include your nickname and a specific reason for the message, so someone else cannot re-use it for a different purpose.",
    "sign_message_confirm": "Sign",
    "sign_message_cancel": "Cancel",
    "sign_message_pin_title": "Enter PIN to confirm",
    "connected_title": "Connected to\\nMEW web",
    "connected_text": "Please use MEW website on your\\ncomputer, or disconnect to get back to\\nMEW wallet app.",
    "connected_disconnect_button": "Disconnect",
    "scan_ethereum_address": "Scan Ethereum address codes\\nto send funds",
    "scan_mewconnect_code": "Scan MEWconnect code to connect to\\nMyEtherWallet.com on desktop",
    "scan_connect_desktop": "How to connect to MEW web",
    "scan_connecting_text": "Creating encrypted peer-to-peer\\nconnection with MEW desktop",
    "scan_connecting_title": "Connecting…",
    "scan_error_text": "Can\\'t connect",
    "scan_text_or": "or",
    "scan_qr_expired_title": "QR code has expired",
    "scan_qr_expired_description": "Please try to refresh webpage with the\\nQR code and scan again.",
    "manage_accounts_toolbar": "Управление счетами",
    "manage_accounts_edit": "Edit",
    "manage_accounts_add": "Добавить счет",
    "manage_accounts_edit_title": "Редактировать",
    "manage_accounts_index": "Address index:",
    "manage_accounts_hidden": "Hidden",
    "settings_and_support_toolbar": "Settings and support",
    "settings_and_support_text_1": "Contact support",
    "settings_and_support_text_2": "View my recovery phrase",
    "settings_and_support_text_3": "Settings",
    "settings_and_support_text_4": "MyEtherWallet.com",
    "settings_and_support_text_5": "Rate the app",
    "settings_and_support_text_6": "MEW on Telegram",
    "settings_and_support_text_7": "Telegram stickers",
    "settings_and_support_text_8": "MEW on Twitter",
    "settings_and_support_text_9": "Privacy and terms",
    "settings_and_support_version": "Version %s (%d)",
    "settings_and_support_copyright": "© 2018–%tY by MyEtherWallet Inc.",
    "settings_and_support_reset_wallet": "Reset wallet",
    "settings_and_support_pin_title": "Enter PIN to view",
    "settings_and_support_biometry_title": "Confirm to view",
    "settings_and_support_fingerprint": "Biometry authentication",
    "settings_and_support_reset_wallet_notice": "Resetting wallet will remove all keys saved in local vault and bring you back to the app\\'s start screen.",
    "settings_toolbar": "Settings",
    "manage_details_toolbar": "Информация о счете",
    "manage_details_index": "Address index:",
    "manage_details_account_name": "Название счета",
    "manage_details_example": "Например: Личные сбережения, Работа, Инвестиции, Секретный счет,\\u00A0и\\u00A0т.\\u00A0п.",
    "manage_details_hide": "Скрыть на главном экране",
    "manage_details_derivation_path": "Derivation path:",
    "reset_wallet_title": "⚠ Warning: you can lose your account and funds forever",
    "reset_wallet_message": "Don\\'t reset if you didn\\'t make a backup, as there will be NO WAY to restore your account after you reset.",
    "receive_funds_title_one_address": "My public address to receive funds",
    "receive_funds_share": "Share",
    "receive_funds_copy": "Copy",
    "receive_funds_address_copied": "Address copied",
    "receive_funds_address_share": "Choose application",
    "enter_recovery_phrase_title": "Enter your recovery phrase",
    "enter_recovery_phrase_edit_text": "Words separated by spaces",
    "enter_recovery_phrase_text": "If your recovery phrase is shorter than 24 words (i.e. 12, 15, 18 or 21 words) you can still use it to restore your wallet. Just enter as many words as you have in your phrase.",
    "enter_recovery_phrase_error_wrong": "Wrong recovery phrase",
    "exchange_withdraw": "Withdraw",
    "education_center_title": "Education center",
    "education_center_safety_tips": "Safety tips",
    "education_center_getting_started": "Getting Started",
    "education_center_security": "Security",
    "education_center_blockchain": "Blockchain",
    "education_center_getting_started_text_1": "Absolute Beginner",
    "education_center_getting_started_text_2": "Your Crypto Minesweeper: Most common support inquiries",
    "education_center_security_text_1": "What crypto wallets mean when they say they are not a bank",
    "education_center_security_text_2": "Are mobile crypto wallets safe?",
    "education_center_blockchain_text_1": "Ethereum Tokens 101",
    "education_center_blockchain_text_2": "Stablecoins: The What’s What",
    "education_center_blockchain_text_3": "Understanding Blockchain Changes: Forks",
    "education_center_blockchain_text_4": "Understanding Blockchain Changes: Testnets and Mainnets",
    "education_center_tips": "Tips",
    "education_center_tips_text_1": "Why is my transaction pending for so long?",
    "education_center_tips_text_2": "How do I cash out?",
    "education_center_mewtopia_title": "MEWtopia",
    "education_center_mewtopia_text": "Update your brain \\nto the latest firmware.",
    "education_center_knowledge_base_title": "Knowledge Base",
    "education_center_knowledge_base_text": "Lost in crypto? Let us help.",
    "education_center_text_1": "Remember to back up\\nyour wallet. If your\\ndevice gets lost or\\nstolen you will lose all\\nyour funds, unless you\\nmade a backup.",
    "education_center_text_2": "Beware of phishing.\\nScams can be quite\\nclever at times. If\\nsomething sounds too\\ngood to be true, it\\nprobably is.",
    "education_center_text_3": "Turn on Push\\nNotifications for MEW\\nwallet, to quickly spot\\nany unusual\\ntransactions. 🔔",
    "education_center_text_4": "All transactions remain\\non the blockchain\\nforever and can be\\nseen by anybody. Don’t\\nshare your public\\naddresses widely.",
    "education_center_text_5": "Create multiple\\naccounts to keep your\\nstacks separate (i.e.\\n‘savings’, ‘trading’ etc.),\\nfor improved privacy\\nand convenience.",
    "education_center_text_6": "Make sure to set a PIN\\nthat is hard to guess.\\nDon’t use the same PIN\\nthat you are using to\\nunlock your phone.",
    "education_center_text_7": "Once you made your\\nbackup, don’t give your\\nrecovery phrase to\\nanyone. Don’t enter it\\nin any apps. Keep it in a\\nsafe place offline.",
    "education_center_text_8": "Crypto is a rabbit hole.\\nAlways try to educate\\nyourself. Do your own\\nresearch and make\\nyour own decisions.\\nDon’t follow the crowd.",
    "education_center_text_9": "You are your own bank.\\nYou are free to do\\nanything you want, but\\nyou need to be extra\\ncareful. Great power –\\ngreat responsibility. 🕷️",
    "education_center_text_10": "There’re no\\nchargebacks in crypto.\\nIf you sent a wrong\\namount to a wrong\\naddress, its final. No-\\none can reverse that.",
    "education_center_text_11": "Breaks our hearts, but\\nit’s impossible for us to\\nrestore your PIN if you\\nlose it. We can’t\\nrecover any lost funds\\neither. 💔",
    "education_center_text_12": "Never tell people how\\nmuch crypto you have.\\nThis might put a target\\non your back.",
    "education_center_text_13": "Crypto markets are not\\nas mature as traditional\\nones and can be easily\\nmanipulated. Don’t\\nrush and make your\\nown decisions.",
    "education_center_text_14": "Don’t forget that we\\nare here for you.\\nIf you have any questions or\\nconcerns, please reach\\nout to our <a href=\"mailto:support@myetherwallet.com\">support<\/a>",
    "add_account_heading": "Добавить счет",
    "safety_and_security_title": "Your safety and\\nsecurity is our\\n#1 priority",
    "safety_and_security_text_1": "We don’t support keystore file and private key imports in MEW wallet app, as they are highly unsafe.",
    "safety_and_security_text_2": "(Note that keystore file and private key are still available methods of access on MyEtherWallet.com, but are not recommended unless using MEW offline)",
    "safety_and_security_text_3": "For maximum security its best to create a new wallet directly in MEW wallet app, same as if you just got a new hardware wallet. That way you can be sure your keys never leave your device.",
    "safety_and_security_text_4": "If you want to access funds in one of your existing wallets via MEW wallet, the most secure way is to create a new wallet and transfer your ETH and Tokens to the new wallet.",
    "safety_and_security_text_5": "Using your existing private key considerably reduces your security.",
    "recovery_phrase_handy_title": "Do you have your recovery phrase handy?",
    "recovery_phrase_handy_text": "Recovery phrase is a 24 word phrase that you wrote down when you backed up your wallet.",
    "recovery_phrase_handy_continue": "Continue",
    "restore_existing_title": "Restore existing wallet",
    "restore_existing_recovery_phrase": "Use recovery phrase",
    "restore_existing_options": "Other options",
    "restore_existing_text": "i.e. keystore file, private key etc.",
    "restore_dialog_text": "We restored your main account automatically, if you had more than one account, and want to restore all of them, please add the other accounts manually by tapping \\'Add account\\' button which you will see when you scroll the cards to the left.",
    "default_notifications_channel_id": "Default notifications channel",
    "buy_ether_title": "Buy Ether with a bank card",
    "buy_ether_fee_simplex": "Purchase includes fee: 5.25% or $10 min",
    "buy_ether_fee_wyre": "%s fee will be added to your purchase",
    "buy_ether_text_2": "We support Google Pay and credit card payments",
    "buy_ether_text_3": "All payments are securely processed by Wyre.",
    "buy_ether_text_4": "Purchase will be done via Simplex\\nApproximate fee is already included in this rate",
    "buy_ether_fiat_custom": "Custom",
    "buy_ether_balance_custom": "$%s max",
    "buy_ether_button_buy_now": "Buy now",
    "buy_ether_button_simplex_min": "$50 minimum purchase",
    "buy_ether_button_choose_amount": "Choose amount",
    "buy_ether_button_creating_order": "Creating order",
    "custom_amount_toolbar": "Custom amount",
    "lock_biometry_title": "Sign in",
    "lock_forgot_pin": "Forgot PIN?",
    "lock_forgot_pin_text": "Unfortunately, as we mentioned when you were creating your PIN, there’s no ‘Restore PIN’ button, however, if you created a backup for your wallet, you can restore your wallet using your recovery phrase and set a new PIN once it’s restored.",
    "lock_restore_wallet": "Restore Wallet",
    "lock_pin_locked_message": "Too many attempts, please wait for %s",
    "mew_connect_password_dialog_text": "Enter your MEWconnect password to finish import",
    "mew_connect_password_dialog_positive_button": "Import",
    "mewconnect_import_dialog_title": "Import your existing\\nMEWconnect account",
    "mewconnect_import_dialog_text": "It looks like you are already using MEWconnect app. You can securely import your existing MEWconnect account and use it here from now on.",
    "mewconnect_import_update_text": "Please update MEWconnect app in order to import.",
    "mewconnect_import_update_confirm": "Update",
    "mewconnect_import_dialog_ok": "Import",
    "mewconnect_import_dialog_cancel": "Create a fresh wallet",
    "mewconnect_import_no_permissions": "Import permission denied. Please allow it in settings",
    "mew_connect_password_dialog_error": "Wrong password",
    "rate_title": "Enjoying our app so far?",
    "rate_text": "Let us know how you feel, your feedback is important to us.",
    "rate_button_rate": "Sure, I\\'ll rate it",
    "rate_button_feedback": "I have feedback",
    "rate_subject": "MEW wallet %s (%d) for Android feedback",
    "debug_deny_screenshots": "Deny screenshots",
    "debug_crash": "Crash app",
    "debug_was_crashed": "Crash detected",
    "debug_crash_show": "Show",
    "debug_wasnt_crashed": "No crashes detected",
    "debug_crash_confirm": "Do you really want to crash app?",
    "debug_show_rater": "Show rater",
    "debug_purchase_type_auto": "Auto (MEW API)",
    "debug_purchase_type_simplex": "Simplex",
    "debug_purchase_type_wyre": "Wyre",
    "debug_purchase_type": "Purchase method",
    "debug_crashes": "Test crashes handling",
    "debug_api_type": "Environment",
    "debug_environment_type_production": "Production",
    "debug_environment_type_development": "Development",
    "debug_environment_type_staging": "Staging",
    "debug_environment_type_qa": "QA",
    "debug_environment_type_ropsten": "Development + Ropsten",
    "debug_api_analytics": "API request (total \/ errors)",
    "debug_add_address": "Add address (no sign, no history)",
    "debug_add": "Add",
    "debug_add_address_success": "Address created",
    "buy_title": "Buy Ether",
    "buy_button": "Buy with credit card",
    "buy_loading_error": "Buy Ether failed",
    "buy_webview_upload_error": "Unable to open file chooser",
    "buy_webview_rationale": "Please enable files access for MEWconnect",
    "history_title": "Purchase history",
    "buy_history_exchange": "Биржа",
    "buy_history_buy_ether": "Buy Ether",
    "buy_history_card": "Visa or Mastercard",
    "buy_history": "History",
    "buy_history_text": "Your recent swaps and crypto\\npurchases will be shown here",
    "buy_history_item_status_complete": "Complete",
    "buy_history_item_status_processing": "Processing",
    "buy_history_item_status_failed": "Failed",
    "buy_history_accounts_title": "Deposit Ether to:",
    "buy_history_buy_create_wallet_title": "Please create a wallet to buy Ether",
    "buy_history_buy_create_wallet_description": "You need a wallet to hold Ether once you purchased it.",
    "buy_history_swap_create_wallet_title": "Please create a wallet to swap tokens",
    "buy_history_swap_create_wallet_description": "You need a wallet to hold Ether and all ERC-20 tokens.",
    "buy_history_create_wallet_button": "Create a wallet",
    "advanced_features_toolbar": "Advanced features",
    "advanced_features_swap_and_trade": "Swap & trade",
    "advanced_features_sign_messages": "Sign messages",
    "advanced_features_borrow_crypto": "Borrow crypto and earn interest",
    "advanced_features_register_names": "Register ENS names",
    "advanced_features_interact_dapps": "Interact with DApps",
    "advanced_features_deploy_smart_contracts": "Deploy smart contracts",
    "advanced_features_title": "Get all the power of MEW web",
    "advanced_features_text_1": "Connect to MyEtherWallet.com to use all of its extended features while safely keeping your keys on your mobile device.",
    "advanced_features_text_2": "Features available when connected to MEW web",
    "advanced_features_button": "Connect to MEW web",
    "advanced_features_create_wallet_title": "Please create a wallet",
    "advanced_features_create_wallet_description": "You need a wallet to connect to MEW web.",
    "capitalize_market_cap": "Market cap",
    "capitalize_volume": "24h volume",
    "capitalize_supply": "Circulating supply",
    "capitalize_total_supply": "Total supply",
    "capitalize_swap_button": "Swap",
    "capitalize_buy_more_button": "Buy more ether",
    "whats_new_title": "What’s new"
}